[
	{
		"article_id": "25818",
		"url": "10/88/25818",
		"article_title": "Project Management Team",
		"publish_year": "",
		"description": "",
		"volume_name": "ABOUT",
		"subsection_name": "Project Management Team",
		"photos": [{ "photo": null, "desc": null }],
		"vids": [],
		"text": "<div class=\"position\">Project Director\r\n<div class=\"staffNames\"><span>Chris B. Millado </span></div>\r\n\r\n<div class=\"staffNames\">&nbsp;</div>\r\n\r\n<div class=\"position\">Project Manager\r\n<div class=\"staffNames\"><span>Libertine Santos Dela Cruz </span></div>\r\n\r\n<div class=\"staffNames\">&nbsp;</div>\r\n\r\n<div class=\"position\">Content Manager</div>\r\n\r\n<div class=\"staffNames\"><span>Elmer L. Gatchalian </span></div>\r\n\r\n<div class=\"staffNames\">&nbsp;</div>\r\n\r\n<div class=\"staffNames\"><span><b>Project Staff</b></span></div>\r\n\r\n<div class=\"staffNames\">&nbsp;</div>\r\n\r\n<div class=\"position\">Technical Head</div>\r\n\r\n<div class=\"staffNames\"><span>Joel P. Bermudez</span></div>\r\n\r\n<div class=\"staffNames\">&nbsp;</div>\r\n\r\n<div class=\"position\">CCP EPA Publication Coordination and Administration\r\n<div class=\"staffNames\"><span>Jhoanne Kristine A. Vinuya, Head </span></div>\r\n\r\n<div class=\"staffNames\"><span>Melanie Lu San Jose </span></div>\r\n\r\n<div class=\"staffNames\">&nbsp;</div>\r\n\r\n<div class=\"position\">CCP Legal and Intellectual Property Rights\r\n<div class=\"staffNames\"><span>Atty George E. Misa </span></div>\r\n\r\n<div class=\"staffNames\"><span>Danielle T. Purzuelo </span></div>\r\n\r\n<div class=\"staffNames\">&nbsp;</div>\r\n\r\n<div class=\"position\">CCP Cultural Research and Development\r\n<div class=\"staffNames\"><span>Horacio Cabangon Jr </span></div>\r\n\r\n<div class=\"staffNames\"><span>Sophia Casta&ntilde;eda </span></div>\r\n\r\n<div class=\"staffNames\"><span>Laurence C. Catalan </span></div>\r\n\r\n<div class=\"staffNames\"><span>Luz C. Catalan </span></div>\r\n\r\n<div class=\"staffNames\"><span>Joel Y. Honrada </span></div>\r\n\r\n<div class=\"staffNames\"><span>Alyssa P. Maglines </span></div>\r\n\r\n<div class=\"staffNames\"><span>Cierra Mortega </span></div>\r\n\r\n<div class=\"staffNames\"><span>John Paul A. Pabustan </span></div>\r\n\r\n<div class=\"staffNames\"><span>Immanuel Soquerata </span></div>\r\n\r\n<div class=\"staffNames\"><span>Austin Rose Tandog </span></div>\r\n\r\n<div class=\"staffNames\"><span>Leila S. Vibal </span></div>\r\n\r\n<div class=\"staffNames\"><span>Trixia Anne Zapater </span></div>\r\n\r\n<div class=\"staffNames\">&nbsp;</div>\r\n\r\n<div class=\"position\">CCP Library and Archives\r\n<div class=\"staffNames\"><span>Alice M. Esteves, Head</span></div>\r\n\r\n<div class=\"staffNames\"><span>Danilo Nataba </span></div>\r\n\r\n<div class=\"staffNames\"><span>Cherry Nocum </span></div>\r\n\r\n<div class=\"staffNames\"><span>Milagros E. Pasion </span></div>\r\n\r\n<div class=\"staffNames\"><span>Richelle P. Revestir </span></div>\r\n\r\n<div class=\"staffNames\">&nbsp;</div>\r\n\r\n<div class=\"position\">With the support of the\r\n<div class=\"staffNames\"><span>CCP Office of the President</span></div>\r\n\r\n<div class=\"staffNames\"><span>CCP Office of the Artistic Director</span></div>\r\n\r\n<div class=\"staffNames\"><span>CCP Visual Arts and Museum Division </span></div>\r\n\r\n<div class=\"staffNames\"><span>CCP Administrative Services Department </span></div>\r\n\r\n<div class=\"staffNames\"><span>CCP Financial Services Department</span></div>\r\n\r\n<div class=\"staffNames\"><span>CCP Marketing Department</span></div>\r\n\r\n<div class=\"staffNames\"><span>CCP Human Resource Management Department</span></div>\r\n\r\n<p style=\"text-align:justify; margin:0in 0in 0.0001pt\">&nbsp;</p>\r\n\r\n<p align=\"center\" style=\"text-align:center; margin:0in 0in 0.0001pt\">&nbsp;</p>\r\n\r\n<div class=\"staffNames\">&nbsp;</div>\r\n</div>\r\n</div>\r\n</div>\r\n</div>\r\n</div>\r\n</div>\r\n</div>\r\n",
		"category": 11,
		"article": [
			{
				"type": "paragraph",
				"value": "Project Director\n<div class=\"staffNames\"><span>Chris B. Millado </span></div>\n\n<div class=\"staffNames\">&#xA0;</div>\n\n<div class=\"position\">Project Manager\n<div class=\"staffNames\"><span>Libertine Santos Dela Cruz </span></div>\n\n<div class=\"staffNames\">&#xA0;</div>\n\n<div class=\"position\">Content Manager</div>\n\n<div class=\"staffNames\"><span>Elmer L. Gatchalian </span></div>\n\n<div class=\"staffNames\">&#xA0;</div>\n\n<div class=\"staffNames\"><span><b>Project Staff</b></span></div>\n\n<div class=\"staffNames\">&#xA0;</div>\n\n<div class=\"position\">Technical Head</div>\n\n<div class=\"staffNames\"><span>Joel P. Bermudez</span></div>\n\n<div class=\"staffNames\">&#xA0;</div>\n\n<div class=\"position\">CCP EPA Publication Coordination and Administration\n<div class=\"staffNames\"><span>Jhoanne Kristine A. Vinuya, Head </span></div>\n\n<div class=\"staffNames\"><span>Melanie Lu San Jose </span></div>\n\n<div class=\"staffNames\">&#xA0;</div>\n\n<div class=\"position\">CCP Legal and Intellectual Property Rights\n<div class=\"staffNames\"><span>Atty George E. Misa </span></div>\n\n<div class=\"staffNames\"><span>Danielle T. Purzuelo </span></div>\n\n<div class=\"staffNames\">&#xA0;</div>\n\n<div class=\"position\">CCP Cultural Research and Development\n<div class=\"staffNames\"><span>Horacio Cabangon Jr </span></div>\n\n<div class=\"staffNames\"><span>Sophia Casta&#xF1;eda </span></div>\n\n<div class=\"staffNames\"><span>Laurence C. Catalan </span></div>\n\n<div class=\"staffNames\"><span>Luz C. Catalan </span></div>\n\n<div class=\"staffNames\"><span>Joel Y. Honrada </span></div>\n\n<div class=\"staffNames\"><span>Alyssa P. Maglines </span></div>\n\n<div class=\"staffNames\"><span>Cierra Mortega </span></div>\n\n<div class=\"staffNames\"><span>John Paul A. Pabustan </span></div>\n\n<div class=\"staffNames\"><span>Immanuel Soquerata </span></div>\n\n<div class=\"staffNames\"><span>Austin Rose Tandog </span></div>\n\n<div class=\"staffNames\"><span>Leila S. Vibal </span></div>\n\n<div class=\"staffNames\"><span>Trixia Anne Zapater </span></div>\n\n<div class=\"staffNames\">&#xA0;</div>\n\n<div class=\"position\">CCP Library and Archives\n<div class=\"staffNames\"><span>Alice M. Esteves, Head</span></div>\n\n<div class=\"staffNames\"><span>Danilo Nataba </span></div>\n\n<div class=\"staffNames\"><span>Cherry Nocum </span></div>\n\n<div class=\"staffNames\"><span>Milagros E. Pasion </span></div>\n\n<div class=\"staffNames\"><span>Richelle P. Revestir </span></div>\n\n<div class=\"staffNames\">&#xA0;</div>\n\n<div class=\"position\">With the support of the\n<div class=\"staffNames\"><span>CCP Office of the President</span></div>\n\n<div class=\"staffNames\"><span>CCP Office of the Artistic Director</span></div>\n\n<div class=\"staffNames\"><span>CCP Visual Arts and Museum Division </span></div>\n\n<div class=\"staffNames\"><span>CCP Administrative Services Department </span></div>\n\n<div class=\"staffNames\"><span>CCP Financial Services Department</span></div>\n\n<div class=\"staffNames\"><span>CCP Marketing Department</span></div>\n\n<div class=\"staffNames\"><span>CCP Human Resource Management Department</span></div>\n\n<p style=\"text-align:justify; margin:0in 0in 0.0001pt\">&#xA0;</p>\n\n<p align=\"center\" style=\"text-align:center; margin:0in 0in 0.0001pt\">&#xA0;</p>\n\n<div class=\"staffNames\">&#xA0;</div>\n</div>\n</div>\n</div>\n</div>\n</div>\n</div>\n"
			},
			{ "type": "author", "value": null },
			{ "type": "see_also", "value": [] },
			{ "type": "sources", "value": [] }
		]
	}
]
